mapbook/__init__.py
mapbook/leafletInterface.py
mapbook/static/README.md
mapbook/static/main.js
mapbook/static/mapbook.css
mapbook/static/mapbook.yaml
mapbook/static/libs/mapbookLeafletWrap.js
mapbook/static/libs/GoldenLayout/goldenlayout-base.css
mapbook/static/libs/GoldenLayout/goldenlayout-light-theme.css
mapbook/static/libs/GoldenLayout/goldenlayout.min.js
mapbook/static/libs/Leaflet/leaflet.css
mapbook/static/libs/Leaflet/leaflet.js
mapbook/static/libs/Leaflet/leaflet.js.map
mapbook/static/libs/Leaflet/images/layers-2x.png
mapbook/static/libs/Leaflet/images/layers.png
mapbook/static/libs/Leaflet/images/marker-icon-2x.png
mapbook/static/libs/Leaflet/images/marker-icon.png
mapbook/static/libs/Leaflet/images/marker-shadow.png
mapbook/static/libs/Leaflet.Coordinates/Leaflet.Coordinates-0.1.5.css
mapbook/static/libs/Leaflet.Coordinates/Leaflet.Coordinates-0.1.5.min.js
mapbook/static/libs/Leaflet.Coordinates/Leaflet.Coordinates-0.1.5.min.mb.js
mapbook/static/libs/Leaflet.Coordinates/Leaflet.Coordinates-0.1.5.min.origin.js
mapbook/static/libs/Leaflet.VectorGrid/Leaflet.VectorGrid.bundled.js
mapbook/static/libs/Leaflet.draw/Leaflet.draw_bundle.js
mapbook/static/libs/Leaflet.draw/leaflet.draw.css
mapbook/static/libs/Leaflet.draw/images/spritesheet-2x.png
mapbook/static/libs/Leaflet.draw/images/spritesheet.png
mapbook/static/libs/Leaflet.draw/images/spritesheet.svg
mapbook/static/libs/handsontable/handsontable.full.min.css
mapbook/static/libs/handsontable/handsontable.full.min.js
mapbook/static/libs/handsontable/handsontable.min.css
mapbook/static/libs/handsontable/handsontable.min.js
mapbook/static/libs/plotly/plotly-latest.min.js
mapbook-0.0.3.data/data/etc/jupyter/jupyter_notebook_config.d/mapbook.json
mapbook-0.0.3.data/data/etc/jupyter/nbconfig/notebook.d/mapbook.json
mapbook-0.0.3.data/data/share/jupyter/nbextensions/mapbook/main.js
mapbook-0.0.3.dist-info/LICENSE
mapbook-0.0.3.dist-info/METADATA
mapbook-0.0.3.dist-info/WHEEL
mapbook-0.0.3.dist-info/top_level.txt
mapbook-0.0.3.dist-info/RECORD
