Metadata-Version: 2.1
Name: mapbook
Version: 0.0.3
Summary: Windows Manager for Jupyter Notebook
Home-page: UNKNOWN
Author: Jiangping He
Author-email: johnbin.ho@gmail.com
License: UNKNOWN
Platform: UNKNOWN
Classifier: Programming Language :: Python :: 3
Classifier: License :: OSI Approved :: MIT License
Classifier: Operating System :: OS Independent
